mindhunter/__init__.py
mindhunter/mindhunter.py
mindhunter/statistics/__init__.py
mindhunter/statistics/distributions.py
mindhunter/statistics/hypothesis.py
mindhunter/utils/__init__.py
mindhunter/utils/toolkit.py
mindhunter/visualization/__init__.py
mindhunter/visualization/stat_plotter.py
mindhunter/visualization/visualizer.py
mindhunter-0.1.1.dist-info/METADATA
mindhunter-0.1.1.dist-info/WHEEL
mindhunter-0.1.1.dist-info/licenses/LICENSE
mindhunter-0.1.1.dist-info/RECORD
