Metadata-Version: 2.4
Name: mindhunter
Version: 0.1.1
Summary: DataFrame extensions for data analysis.
License-File: LICENSE
Requires-Python: >=3.12
Requires-Dist: faker>=37.8.0
Requires-Dist: matplotlib>=3.10.6
Requires-Dist: numpy>=2.3.3
Requires-Dist: pandas>=2.3.3
Requires-Dist: patsy>=1.0.1
Requires-Dist: pytest-cov>=4.1.0
Requires-Dist: pytest>=7.4.0
Requires-Dist: scipy>=1.10.0
Requires-Dist: seaborn>=0.13.2
Requires-Dist: statsmodels>=0.14.5
